visualize_links/__init__.py
visualize_links/ui.py
visualize_links/lldb_plugin/__init__.py
visualize_links/lldb_plugin/cola_graph.py
visualize_links/lldb_plugin/cola_model.py
visualize_links/lldb_plugin/commands.py
visualize_links/lldb_plugin/graph.py
visualize_links/lldb_plugin/history.py
visualize_links/lldb_plugin/lldb_utils.py
visualize_links/lldb_plugin/model.py
visualize_links/lldb_plugin/served_model.py
visualize_links/lldb_plugin/server.py
visualize_links/static/index.html
visualize_links-1.0.2.dist-info/licenses/LICENSE
visualize_links-1.0.2.dist-info/METADATA
visualize_links-1.0.2.dist-info/WHEEL
visualize_links-1.0.2.dist-info/entry_points.txt
visualize_links-1.0.2.dist-info/top_level.txt
visualize_links-1.0.2.dist-info/RECORD
