Metadata-Version: 2.4
Name: visualize-links
Version: 1.0.2
Summary: An LLDB plugin and web ui to visualize and debug pointer-based data structure programs written in C/C++.
Author-email: Indrajit Banerjee <indra99.acc@gmail.com>
License-Expression: MIT
Project-URL: Homepage, https://github.com/drain99/visualize-links
Project-URL: Repository, https://github.com/drain99/visualize-links
Project-URL: Issues, https://github.com/drain99/visualize-links/issues
Keywords: lldb,visualization,C++
Requires-Python: >=3.8
License-File: LICENSE
Requires-Dist: pydantic>=2.10
Requires-Dist: websockets>=11.0.3
Dynamic: license-file
